arithmetic_jy/__init__.py
arithmetic_jy/arithmetic.py
arithmetic_jy/entry_point.py
arithmetic_jy-0.0.2.dist-info/METADATA
arithmetic_jy-0.0.2.dist-info/WHEEL
arithmetic_jy-0.0.2.dist-info/entry_points.txt
arithmetic_jy-0.0.2.dist-info/top_level.txt
arithmetic_jy-0.0.2.dist-info/RECORD
