Metadata-Version: 2.4
Name: arithmetic_jy
Version: 0.0.2
Summary: A small example package
Author-email: yjiang <1900812927@qq.com>
Project-URL: homepage, https://gitee.com/Eason596/py-package-release-test
Project-URL: repository, https://gitee.com/Eason596/py-package-release-test
Keywords: arithmetic
Requires-Python: >=3.8
Requires-Dist: numpy>=1.24.3
